dlrnapi_client/__init__.py
dlrnapi_client/api_client.py
dlrnapi_client/configuration.py
dlrnapi_client/rest.py
dlrnapi_client/shell.py
dlrnapi_client/ansible/ansible.cfg.example
dlrnapi_client/ansible/dlrn_api.py
dlrnapi_client/ansible/example_playbook.yaml
dlrnapi_client/apis/__init__.py
dlrnapi_client/apis/default_api.py
dlrnapi_client/models/__init__.py
dlrnapi_client/models/agg_query.py
dlrnapi_client/models/ci_agg_vote.py
dlrnapi_client/models/ci_vote.py
dlrnapi_client/models/metrics.py
dlrnapi_client/models/model_import.py
dlrnapi_client/models/params.py
dlrnapi_client/models/params_1.py
dlrnapi_client/models/params_2.py
dlrnapi_client/models/params_3.py
dlrnapi_client/models/promotion.py
dlrnapi_client/models/promotion_query.py
dlrnapi_client/models/repo.py
dlrnapi_client-0.13.1.dist-info/AUTHORS
dlrnapi_client-0.13.1.dist-info/LICENSE
dlrnapi_client-0.13.1.dist-info/METADATA
dlrnapi_client-0.13.1.dist-info/WHEEL
dlrnapi_client-0.13.1.dist-info/entry_points.txt
dlrnapi_client-0.13.1.dist-info/pbr.json
dlrnapi_client-0.13.1.dist-info/top_level.txt
dlrnapi_client-0.13.1.dist-info/RECORD
