Metadata-Version: 2.1
Name: dlrnapi-client
Version: 0.13.1
Summary: Client for DLRN REST API
Home-page: http://www.rdoproject.org/
Author: OpenStack
Author-email: jpena@redhat.com
Project-URL: Bug Tracker, https://github.com/softwarefactory-project/dlrnapi_client/issues
Project-URL: Source Code, https://github.com/softwarefactory-project/dlrnapi_client
Classifier: Environment :: OpenStack
Classifier: Intended Audience :: Information Technology
Classifier: Intended Audience :: System Administrators
Classifier: License :: OSI Approved :: Apache Software License
Classifier: Operating System :: POSIX :: Linux
Classifier: Programming Language :: Python
Classifier: Programming Language :: Python :: 2
Classifier: Programming Language :: Python :: 2.7
Classifier: Programming Language :: Python :: 3
Classifier: Programming Language :: Python :: 3.6
Classifier: Programming Language :: Python :: 3.7
Requires-Python: !=3.0.*,!=3.1.*,!=3.2.*,!=3.3.*,!=3.4.*,>=2.7
License-File: LICENSE
Requires-Dist: certifi (>=14.05.14)
Requires-Dist: six (>=1.10)
Requires-Dist: python-dateutil (>=2.5.3)
Requires-Dist: setuptools (>=21.0.0)
Requires-Dist: urllib3 (>=1.15.1)
Provides-Extra: kerberos
Requires-Dist: gssapi ; extra == 'kerberos'
